wcpan/telegram/__init__.py
wcpan/telegram/api.py
wcpan/telegram/types.py
wcpan/telegram/util.py
wcpan.telegram-0.3.0.dev7.dist-info/LICENSE
wcpan.telegram-0.3.0.dev7.dist-info/METADATA
wcpan.telegram-0.3.0.dev7.dist-info/WHEEL
wcpan.telegram-0.3.0.dev7.dist-info/top_level.txt
wcpan.telegram-0.3.0.dev7.dist-info/RECORD
