Metadata-Version: 2.1
Name: wcpan.telegram
Version: 0.3.0.dev7
Summary: Telegram Bot API with Tornado
Home-page: https://github.com/legnaleurc/wcpan.telegram
Author: Wei-Cheng Pan
Author-email: legnaleurc@gmail.com
License: MIT
Keywords: telegram bot tornado
Platform: UNKNOWN
Classifier: Development Status :: 3 - Alpha
Classifier: Intended Audience :: Developers
Classifier: Topic :: Communications :: Chat
Classifier: License :: OSI Approved :: MIT License
Classifier: Programming Language :: Python :: 3 :: Only
Classifier: Programming Language :: Python :: 3.5
License-File: LICENSE
Requires-Dist: tornado (>=4)
